<annotation>
	<folder>T2</folder>
	<filename>IMG_20190523_191043.jpg</filename>
	<path>C:\Users\administrator\Desktop\T2\IMG_20190523_191043.jpg</path>
	<source>
		<database>Unknown</database>
	</source>
	<size>
		<width>640</width>
		<height>360</height>
		<depth>3</depth>
	</size>
	<segmented>0</segmented>
	<object>
		<name>TOOL</name>
		<pose>Unspecified</pose>
		<truncated>0</truncated>
		<difficult>0</difficult>
		<bndbox>
			<xmin>197</xmin>
			<ymin>50</ymin>
			<xmax>492</xmax>
			<ymax>319</ymax>
		</bndbox>
	</object>
	<object>
		<name>TOOL</name>
		<pose>Unspecified</pose>
		<truncated>0</truncated>
		<difficult>0</difficult>
		<bndbox>
			<xmin>223</xmin>
			<ymin>84</ymin>
			<xmax>465</xmax>
			<ymax>338</ymax>
		</bndbox>
	</object>
	<object>
		<name>TOOL</name>
		<pose>Unspecified</pose>
		<truncated>0</truncated>
		<difficult>0</difficult>
		<bndbox>
			<xmin>224</xmin>
			<ymin>37</ymin>
			<xmax>493</xmax>
			<ymax>301</ymax>
		</bndbox>
	</object>
</annotation>
